cetra/__init__.py
cetra/cetra.cu
cetra/cetra.py
cetra/transit_model_b32.npz
cetra/transit_model_b93.npz
cetra/transit_model_b99.npz
cetra/utils.py
cetra-1.0.dist-info/licenses/LICENSE
cetra-1.0.dist-info/METADATA
cetra-1.0.dist-info/WHEEL
cetra-1.0.dist-info/top_level.txt
cetra-1.0.dist-info/RECORD
